fantasy_hockey_notifier_cdk/__init__.py
fantasy_hockey_notifier_cdk/py.typed
fantasy_hockey_notifier_cdk/_jsii/__init__.py
fantasy_hockey_notifier_cdk/_jsii/fantasy-hockey-notifier-cdk@2.0.63.jsii.tgz
fantasy_hockey_notifier_cdk-2.0.63.dist-info/LICENSE
fantasy_hockey_notifier_cdk-2.0.63.dist-info/METADATA
fantasy_hockey_notifier_cdk-2.0.63.dist-info/WHEEL
fantasy_hockey_notifier_cdk-2.0.63.dist-info/top_level.txt
fantasy_hockey_notifier_cdk-2.0.63.dist-info/RECORD
