Metadata-Version: 2.1
Name: fantasy-hockey-notifier-cdk
Version: 2.0.63
Summary: AWS CDK construct to send notifications for adds, drops, and trades in an ESPN Fantasy Hockey league
Home-page: https://github.com/ftalburt/fantasy-hockey-notifier-cdk.git#readme
Author: Forrest Talburt
License: MIT
Project-URL: Source, https://github.com/ftalburt/fantasy-hockey-notifier-cdk.git
Classifier: Intended Audience :: Developers
Classifier: Operating System :: OS Independent
Classifier: Programming Language :: JavaScript
Classifier: Programming Language :: Python :: 3 :: Only
Classifier: Programming Language :: Python :: 3.7
Classifier: Programming Language :: Python :: 3.8
Classifier: Programming Language :: Python :: 3.9
Classifier: Programming Language :: Python :: 3.10
Classifier: Programming Language :: Python :: 3.11
Classifier: Typing :: Typed
Classifier: Development Status :: 5 - Production/Stable
Classifier: License :: OSI Approved
Requires-Python: ~=3.7
License-File: LICENSE
Requires-Dist: aws-cdk-lib (<3.0.0,>=2.30.0)
Requires-Dist: cdk-iam-floyd (<0.495.0,>=0.494.0)
Requires-Dist: constructs (<11.0.0,>=10.0.5)
Requires-Dist: jsii (<2.0.0,>=1.78.1)
Requires-Dist: publication (>=0.0.3)
Requires-Dist: typeguard (~=2.13.3)
